Design.v
`timescale 1ns / 1ps
//////////////////////////////////////////////////////////////////////////////////
// Company: 
// Engineer: 
// 
// Create Date: 13.04.2026 16:24:08
// Design Name: 
// Module Name: BCDt7Sdecoder
// Project Name: 
// Target Devices: 
// Tool Versions: 
// Description: 
// 
// Dependencies: 
// 
// Revision:
// Revision 0.01 - File Created
// Additional Comments:
// 
//////////////////////////////////////////////////////////////////////////////////


module BCDt7Sdecoder(
   input [3:0]a_i, 
   output reg [6:0]y_o
);
//starting from top to clockwise then centre at last, abcdefg
always@(*)
case (a_i)
4'b0000: y_o = 7'b1111110; //0
4'b0001: y_o = 7'b0110000; //1
4'b0010: y_o = 7'b1101101; //2
4'b0011: y_o = 7'b1111001; //3
4'b0100: y_o = 7'b0110011; //4
4'b0101: y_o = 7'b1011011; //5
4'b0110: y_o = 7'b1011111; //6
4'b0111: y_o = 7'b1110000; //7
4'b1000: y_o = 7'b1111111; //8
4'b1001: y_o = 7'b1111011; //9
//4'b1010: y_o = 7'b1111111; //to verify if self checking in testbench is working or not
default: y_o = 7'b0000000; //All OFF
endcase

endmodule

Testbench.v
`timescale 1ns / 1ps
//////////////////////////////////////////////////////////////////////////////////
// Company: 
// Engineer: 
// 
// Create Date: 13.04.2026 16:24:34
// Design Name: 
// Module Name: tb_BCDt7Sdecoder
// Project Name: 
// Target Devices: 
// Tool Versions: 
// Description: 
// 
// Dependencies: 
// 
// Revision:
// Revision 0.01 - File Created
// Additional Comments:
// 
//////////////////////////////////////////////////////////////////////////////////


module tb_BCDt7Sdecoder();
reg [3:0]a_i;
wire [6:0]y_o;

//net(s)
reg [6:0]exp_result; //expected output
integer i; //for loop in input feeding

//instantiation
BCDt7Sdecoder DUT(.a_i(a_i), 
   .y_o(y_o));

initial begin //feeding inputs
a_i = 4'b0000; //0
#2 if(y_o !== exp_result) //self checking
      $display("Error | Time: %0t | BCD: %b (%d) | Expected: %b,  Coded: %b", $time, a_i, a_i, exp_result, y_o);
for(i = 1; i < 16; i = i + 1) begin //1-15
   #3 a_i = i;
   #2 if(y_o !== exp_result) //self checking
         $display("Error | Time: %0t | BCD: %b (%d) | Expected: %b,  Coded: %b", $time, a_i, a_i, exp_result, y_o);
end
#5 $finish;
end

//expected results -- for self checking
always@(*)
case (a_i)
4'b0000: exp_result = 7'b1111110; //0
4'b0001: exp_result = 7'b0110000; //1
4'b0010: exp_result = 7'b1101101; //2
4'b0011: exp_result = 7'b1111001; //3
4'b0100: exp_result = 7'b0110011; //4
4'b0101: exp_result = 7'b1011011; //5
4'b0110: exp_result = 7'b1011111; //6
4'b0111: exp_result = 7'b1110000; //7
4'b1000: exp_result = 7'b1111111; //8
4'b1001: exp_result = 7'b1111011; //9
default: exp_result = 7'b0000000; //all off
endcase

initial begin //capture
//$monitor("Time: %0t | BCD: %b (%0d) | Coded Out: %b", $time, a_i, a_i, y_o); //manual checking
$dumpfile("BCDt7Sdecoder.vcd");
$dumpvars(0, tb_BCDt7Sdecoder);
end

endmodule

BCDt7Sdecoder.vcd
$date
   Wed Apr 15 12:51:02 2026
$end

$version
  2025.2
  $dumpfile ("BCDt7Sdecoder.vcd") 
$end

$timescale
  1ps
$end

$scope module tb_BCDt7Sdecoder $end
$var reg 4 ! a_i [3:0] $end
$var wire 7 " y_o [6:0] $end
$var reg 7 # exp_result [6:0] $end
$var integer 32 $ i [31:0] $end
$scope module DUT $end
$var wire 4 % a_i [3:0] $end
$var reg 7 & y_o [6:0] $end
$upscope $end
$upscope $end
$enddefinitions $end

#0
$dumpvars
b0 !
b1111110 "
b1111110 #
bx $
b0 %
b1111110 &
$end

#2000
b1 $

#5000
b1 !
b110000 "
b110000 #
b1 %
b110000 &

#7000
b10 $

#10000
b10 !
b1101101 "
b1101101 #
b10 %
b1101101 &

#12000
b11 $

#15000
b11 !
b1111001 "
b1111001 #
b11 %
b1111001 &

#17000
b100 $

#20000
b100 !
b110011 "
b110011 #
b100 %
b110011 &

#22000
b101 $

#25000
b101 !
b1011011 "
b1011011 #
b101 %
b1011011 &

#27000
b110 $

#30000
b110 !
b1011111 "
b1011111 #
b110 %
b1011111 &

#32000
b111 $

#35000
b111 !
b1110000 "
b1110000 #
b111 %
b1110000 &

#37000
b1000 $

#40000
b1000 !
b1111111 "
b1111111 #
b1000 %
b1111111 &

#42000
b1001 $

#45000
b1001 !
b1111011 "
b1111011 #
b1001 %
b1111011 &

#47000
b1010 $

#50000
b1010 !
b1111111 "
b0 #
b1010 %
b1111111 &

#52000
b1011 $

#55000
b1011 !
b0 "
b1011 %
b0 &

#57000
b1100 $

#60000
b1100 !
b1100 %

#62000
b1101 $

#65000
b1101 !
b1101 %

#67000
b1110 $

#70000
b1110 !
b1110 %

#72000
b1111 $

#75000
b1111 !
b1111 %

#77000
b10000 $
